fuzzup/2022.04.06-finished-eblocal_converts.csv
fuzzup/__init__.py
fuzzup/datasets.py
fuzzup/fuzz.py
fuzzup/utils.py
fuzzup/whitelists.py
fuzzup-0.5.0.dist-info/LICENSE
fuzzup-0.5.0.dist-info/METADATA
fuzzup-0.5.0.dist-info/WHEEL
fuzzup-0.5.0.dist-info/top_level.txt
fuzzup-0.5.0.dist-info/RECORD
