Metadata-Version: 2.1
Name: fuzzup
Version: 0.5.0
Summary: A Fuzzy Matching Approach for Clustering Strings
Home-page: https://github.com/ebanalyse/fuzzup
Author: Lars Kjeldgaard, Søren Kolbye Jensen
Author-email: lars.kjeldgaard@eb.dk, soren.k.jensen@eb.dk
License: UNKNOWN
Platform: UNKNOWN
Classifier: Programming Language :: Python :: 3
Classifier: License :: OSI Approved :: MIT License
Requires-Python: >=3.7
Requires-Dist: scipy (==1.8.1)
Requires-Dist: pandas (>=1.3.5)
Requires-Dist: numpy (==1.21.6)
Requires-Dist: rapidfuzz (==2.0.4)
Requires-Dist: tqdm (==4.64.0)
Requires-Dist: cvr (==0.2.0)
Requires-Dist: geopy (==2.2.0)
